{"trial_id": "0214", "hyperparameters": {"space": [{"class_name": "Int", "config": {"name": "num_hidden_layers", "default": null, "conditions": [], "min_value": 2, "max_value": 6, "step": 1, "sampling": "linear"}}, {"class_name": "Choice", "config": {"name": "regularizer", "default": "none", "conditions": [], "values": ["none", "l1", "l2", "l1_l2"], "ordered": false}}, {"class_name": "Float", "config": {"name": "dropout_rate", "default": 0.0, "conditions": [], "min_value": 0.0, "max_value": 0.5, "step": 0.1, "sampling": "linear"}}, {"class_name": "Int", "config": {"name": "units_0", "default": null, "conditions": [], "min_value": 10, "max_value": 100, "step": 10, "sampling": "linear"}}, {"class_name": "Int", "config": {"name": "units_1", "default": null, "conditions": [], "min_value": 10, "max_value": 100, "step": 10, "sampling": "linear"}}, {"class_name": "Choice", "config": {"name": "learning_rate", "default": 0.01, "conditions": [], "values": [0.01], "ordered": true}}, {"class_name": "Float", "config": {"name": "l2_value", "default": 0.0001, "conditions": [], "min_value": 0.0001, "max_value": 0.01, "step": null, "sampling": "linear"}}, {"class_name": "Int", "config": {"name": "units_2", "default": null, "conditions": [], "min_value": 10, "max_value": 100, "step": 10, "sampling": "linear"}}, {"class_name": "Int", "config": {"name": "units_3", "default": null, "conditions": [], "min_value": 10, "max_value": 100, "step": 10, "sampling": "linear"}}, {"class_name": "Float", "config": {"name": "l1_value", "default": 0.0001, "conditions": [], "min_value": 0.0001, "max_value": 0.01, "step": null, "sampling": "linear"}}, {"class_name": "Int", "config": {"name": "units_4", "default": null, "conditions": [], "min_value": 10, "max_value": 100, "step": 10, "sampling": "linear"}}, {"class_name": "Int", "config": {"name": "units_5", "default": null, "conditions": [], "min_value": 10, "max_value": 100, "step": 10, "sampling": "linear"}}, {"class_name": "Float", "config": {"name": "l1_l1l2_value", "default": 0.0001, "conditions": [], "min_value": 0.0001, "max_value": 0.01, "step": null, "sampling": "linear"}}, {"class_name": "Float", "config": {"name": "l2_l1l2_value", "default": 0.0001, "conditions": [], "min_value": 0.0001, "max_value": 0.01, "step": null, "sampling": "linear"}}], "values": {"num_hidden_layers": 5, "regularizer": "l1_l2", "dropout_rate": 0.0, "units_0": 50, "units_1": 70, "learning_rate": 0.01, "l2_value": 0.0006539599410997948, "units_2": 10, "units_3": 10, "l1_value": 0.0028370748641825512, "units_4": 80, "units_5": 50, "l1_l1l2_value": 0.0022151292561013356, "l2_l1l2_value": 0.004537808526785728, "tuner/epochs": 12, "tuner/initial_epoch": 0, "tuner/bracket": 2, "tuner/round": 0}}, "metrics": {"metrics": {"loss": {"direction": "min", "observations": [{"value": [18.311880111694336], "step": 8}]}, "val_loss": {"direction": "min", "observations": [{"value": [17.661678314208984], "step": 8}]}}}, "score": 17.661678314208984, "best_step": 8, "status": "COMPLETED", "message": null}